{"content":[{"id":"4be6398d","settings":{"flex_direction":"column","min_height":{"unit":"px","size":820,"sizes":[]},"flex_justify_content":"center","flex_align_items":"center","background_image":{"id":"","url":"","source":"url","size":"","alt":""},"background_position":"center center","background_size":"cover","background_overlay_background":"classic","__globals__":{"background_color":"","background_overlay_color":"globals\/colors?id=astglobalcolor1"},"css_classes":"hero","flex_gap":{"column":"48","row":"48","isLinked":true,"unit":"px","size":48},"min_height_tablet":{"unit":"px","size":720,"sizes":[]},"pa_condition_repeater":[],"flex_gap_mobile":{"column":"32","row":"32","isLinked":true,"unit":"px","size":32}},"elements":[{"id":"d358f7e","settings":{"image":{"url":"\/wp-content\/plugins\/obsia\/designs\/aspera\/images\/law.webp","id":"","size":"","source":"url"},"image_size":"full","align":"center","width":{"unit":"%","size":100,"sizes":[]},"_element_width":"inherit","_element_custom_width":{"unit":"%","size":100,"sizes":[]},"_flex_align_self":"center","_flex_size":"grow","_position":"absolute","_z_index":-1,"_element_id":"ob-hero-bg"},"elements":[],"isInner":false,"widgetType":"image","elType":"widget"},{"id":"38b5413","settings":{"content_width":"full","flex_align_items":"center","flex_gap":{"column":"24","row":"24","isLinked":true,"unit":"px","size":24},"padding":{"unit":"px","top":"0","right":"0","bottom":"0","left":"0","isLinked":true},"pa_condition_repeater":[],"flex_gap_mobile":{"column":"16","row":"16","isLinked":true,"unit":"px","size":16}},"elements":[{"id":"f8c5dd4","settings":{"title":"Aspera","title_color":"#FFFFFF","header_size":"h1","__globals__":{"typography_typography":""},"typography_font_family":"Roboto","typography_font_weight":"600","pa_condition_repeater":[],"_element_id":"ob-hero-title"},"elements":[],"isInner":false,"widgetType":"heading","elType":"widget"},{"id":"32406fd7","settings":{"editor":"<p>Stop jumping between dozens of tabs. Manage your projects, track your progress, and collaborate with your team in one unified workspace designed for modern professionals.<\/p>","paragraph_spacing":{"unit":"px","size":0,"sizes":[]},"_margin":{"unit":"px","top":"0","right":"0","bottom":"0","left":"0","isLinked":true},"_padding":{"unit":"px","top":"0","right":"0","bottom":"0","left":"0","isLinked":true},"__globals__":{"text_color":"","typography_typography":""},"text_color":"#E9E9E9","typography_font_family":"Roboto Slab","typography_font_weight":"400","pa_condition_repeater":[],"_element_id":"ob-hero-shortdescription"},"elements":[],"isInner":false,"widgetType":"text-editor","elType":"widget"}],"isInner":true,"elType":"container"},{"id":"79bd3d07","settings":{"text":"Click here","_padding":{"unit":"px","top":"0","right":"0","bottom":"0","left":"0","isLinked":true},"border_border":"solid","border_width":{"unit":"px","top":"2","right":"2","bottom":"2","left":"2","isLinked":true},"border_radius":{"unit":"px","top":"0","right":"0","bottom":"0","left":"0","isLinked":true},"__globals__":{"button_text_color":"globals\/colors?id=astglobalcolor3","background_color":"globals\/colors?id=astglobalcolor4","border_color":"globals\/colors?id=astglobalcolor4","button_background_hover_color":"globals\/colors?id=astglobalcolor5","button_hover_border_color":"globals\/colors?id=astglobalcolor5"},"align_mobile":"justify","_element_width_mobile":"inherit","pa_condition_repeater":[],"_element_id":"ob-hero-button"},"elements":[],"isInner":false,"widgetType":"button","elType":"widget"}],"isInner":false,"elType":"container"},{"id":"3e775937","settings":{"flex_direction":"row","flex_gap":{"column":"64","row":"64","isLinked":true,"unit":"px","size":64},"background_background":"classic","__globals__":{"background_color":"globals\/colors?id=astglobalcolor4"},"flex_gap_mobile":{"column":"48","row":"48","isLinked":true,"unit":"px","size":48},"pa_condition_repeater":[],"padding":{"unit":"px","top":"50","right":"50","bottom":"50","left":"50","isLinked":true}},"elements":[{"id":"35f66275","settings":{"content_width":"full","flex_justify_content":"center","flex_gap":{"column":"48","row":"48","isLinked":true,"unit":"px","size":48},"padding":{"unit":"px","top":"0","right":"0","bottom":"0","left":"0","isLinked":true},"flex_gap_mobile":{"column":"32","row":"32","isLinked":true,"unit":"px","size":32},"pa_condition_repeater":[]},"elements":[{"id":"58375317","settings":{"content_width":"full","flex_gap":{"column":"12","row":"12","isLinked":true,"unit":"px","size":12},"padding":{"unit":"px","top":"0","right":"0","bottom":"0","left":"0","isLinked":true},"pa_condition_repeater":[]},"elements":[{"id":"2a84b783","settings":{"title":"Ut Enim Ad Minim Veniam","header_size":"h5","__globals__":{"title_color":"globals\/colors?id=astglobalcolor0"},"pa_condition_repeater":[],"_element_id":"ob-content-tagline"},"elements":[],"isInner":false,"widgetType":"heading","elType":"widget"},{"id":"2f25d1a5","settings":{"title":"Lorem Ipsum Dolor Sit Amet","__globals__":{"title_color":"globals\/colors?id=astglobalcolor2"},"pa_condition_repeater":[],"_element_id":"ob-content-title"},"elements":[],"isInner":false,"widgetType":"heading","elType":"widget"}],"isInner":true,"elType":"container"},{"id":"4fad6b2","settings":{"editor":"<p>Mi tincidunt elit, id quisque ligula ac diam, amet. Vel etiam suspendisse morbi eleifend faucibus eget vestibulum felis. Dictum quis montes, sit sit. Tellus aliquam enim urna, etiam.<\/p><p>Dolor enim eu tortor urna sed duis nulla. Aliquam vestibulum, nulla odio nisl vitae. In aliquet pellentesque aenean hac vestibulum turpis mi bibendum diam. Tempor integer aliquam in vitae malesuada.<\/p>","__globals__":{"text_color":"globals\/colors?id=astglobalcolor3"},"pa_condition_repeater":[],"_element_id":"ob-content-text"},"elements":[],"isInner":false,"widgetType":"text-editor","elType":"widget"},{"id":"248a15bc","settings":{"text":"Click here","align_mobile":"justify","pa_condition_repeater":[],"_element_id":"ob-content-button"},"elements":[],"isInner":false,"widgetType":"button","elType":"widget"}],"isInner":true,"elType":"container"},{"id":"540870bb","settings":{"image":{"id":"","url":"\/wp-content\/plugins\/obsia\/designs\/aspera\/images\/business.webp","source":"url","size":"","alt":""},"align":"center","height":{"unit":"%","size":100,"sizes":[]},"height_tablet":{"unit":"%","size":"","sizes":[]},"height_mobile":{"unit":"px","size":264,"sizes":[]},"object-fit":"cover","_element_width":"inherit","_element_custom_width":{"unit":"%","size":100,"sizes":[]},"_flex_align_self":"center","pa_condition_repeater":[],"_element_id":"ob-content-img"},"elements":[],"isInner":false,"widgetType":"image","elType":"widget"}],"isInner":false,"elType":"container"},{"id":"2d8e3aa0","settings":{"flex_direction":"column","flex_gap":{"column":"64","row":"64","isLinked":true,"unit":"px","size":64},"background_background":"classic","__globals__":{"background_color":""},"pa_condition_repeater":[],"padding":{"unit":"px","top":"50","right":"50","bottom":"50","left":"50","isLinked":true},"background_color":"#F3F3F3"},"elements":[{"id":"286b5d92","settings":{"content_width":"full","flex_direction":"row","flex_justify_content":"space-between","flex_align_items":"center","padding":{"unit":"px","top":"0","right":"0","bottom":"0","left":"0","isLinked":true},"flex_gap":{"column":"32","row":"32","isLinked":true,"unit":"px","size":32},"pa_condition_repeater":[]},"elements":[{"id":"47d9d0ba","settings":{"title":"Lorem Ipsum Dolor Sit Amet","pa_condition_repeater":[],"_element_id":"ob-stepbystep-title"},"elements":[],"isInner":false,"widgetType":"heading","elType":"widget"},{"id":"1c2f9229","settings":{"text":"Click here","align_mobile":"justify","_element_width_mobile":"inherit","pa_condition_repeater":[],"_element_id":"ob-stepbystep-button"},"elements":[],"isInner":false,"widgetType":"button","elType":"widget"}],"isInner":true,"elType":"container"},{"id":"8274443","settings":{"content_width":"full","flex_direction":"row","flex_gap":{"column":"32","row":"32","isLinked":true,"unit":"px","size":32},"padding":{"unit":"px","top":"0","right":"0","bottom":"0","left":"0","isLinked":true},"pa_condition_repeater":[]},"elements":[{"id":"3afbeea7","settings":{"content_width":"full","flex_gap":{"column":"16","row":"16","isLinked":true,"unit":"px","size":16},"padding":{"unit":"px","top":"0","right":"0","bottom":"0","left":"0","isLinked":true},"pa_condition_repeater":[]},"elements":[{"id":"58fe1237","settings":{"title":"01","header_size":"h4","__globals__":{"title_color":"globals\/colors?id=astglobalcolor3"},"pa_condition_repeater":[]},"elements":[],"isInner":false,"widgetType":"heading","elType":"widget"},{"id":"2fd81f7d","settings":{"image":{"id":"","url":"\/wp-content\/plugins\/obsia\/designs\/placeholders\/person1.webp","source":"url","size":"","alt":""},"pa_condition_repeater":[]},"elements":[],"isInner":false,"widgetType":"image","elType":"widget"},{"id":"776ebd10","settings":{"content_width":"full","flex_gap":{"column":"4","row":"4","isLinked":true,"unit":"px","size":4},"padding":{"unit":"px","top":"0","right":"0","bottom":"0","left":"0","isLinked":true},"pa_condition_repeater":[]},"elements":[{"id":"2e567b3b","settings":{"title":"Ut Enim Ad Minim Veniam","header_size":"h5","pa_condition_repeater":[],"_element_id":"ob-stepbystep-step1-title"},"elements":[],"isInner":false,"widgetType":"heading","elType":"widget"},{"id":"19b6a0f3","settings":{"editor":"<p>Mi tincidunt elit, id quisque ligula ac diam, amet. Vel etiam suspendisse morbi eleifend faucibus eget vestibulum felis. Dictum quis montes, sit sit. Tellus aliquam enim urna, etiam.<\/p>","typography_font_weight":"400","paragraph_spacing":{"unit":"px","size":0,"sizes":[]},"__globals__":{"typography_typography":""},"pa_condition_repeater":[],"typography_typography":"custom","_element_id":"ob-stepbystep-step1-description"},"elements":[],"isInner":false,"widgetType":"text-editor","elType":"widget"}],"isInner":true,"elType":"container"},{"id":"30ab17df","settings":{"text":"Learn more","button_text_color":"#0085FF","background_color":"#0085FF00","border_border":"none","text_padding":{"unit":"px","top":"0","right":"0","bottom":"0","left":"0","isLinked":true},"__globals__":{"button_text_color":"globals\/colors?id=astglobalcolor0","background_color":"","hover_color":"globals\/colors?id=astglobalcolor1"},"pa_condition_repeater":[]},"elements":[],"isInner":false,"widgetType":"button","elType":"widget"}],"isInner":true,"elType":"container"},{"id":"6dab0b2f","settings":{"content_width":"full","flex_gap":{"column":"16","row":"16","isLinked":true,"unit":"px","size":16},"padding":{"unit":"px","top":"0","right":"0","bottom":"0","left":"0","isLinked":true},"pa_condition_repeater":[]},"elements":[{"id":"45322e4b","settings":{"title":"02","header_size":"h4","__globals__":{"title_color":"globals\/colors?id=astglobalcolor3"},"pa_condition_repeater":[]},"elements":[],"isInner":false,"widgetType":"heading","elType":"widget"},{"id":"50fd36c9","settings":{"image":{"id":"","url":"\/wp-content\/plugins\/obsia\/designs\/placeholders\/person1.webp","source":"url","size":"","alt":""},"pa_condition_repeater":[]},"elements":[],"isInner":false,"widgetType":"image","elType":"widget"},{"id":"633c966","settings":{"content_width":"full","flex_gap":{"column":"4","row":"4","isLinked":true,"unit":"px","size":4},"padding":{"unit":"px","top":"0","right":"0","bottom":"0","left":"0","isLinked":true},"pa_condition_repeater":[]},"elements":[{"id":"11b1b5c2","settings":{"title":"Ut Enim Ad Minim Veniam","header_size":"h5","pa_condition_repeater":[],"_element_id":"ob-stepbystep-step2-title"},"elements":[],"isInner":false,"widgetType":"heading","elType":"widget"},{"id":"79c0839c","settings":{"editor":"<p>Mi tincidunt elit, id quisque ligula ac diam, amet. Vel etiam suspendisse morbi eleifend faucibus eget vestibulum felis. Dictum quis montes, sit sit. Tellus aliquam enim urna, etiam.<\/p>","typography_font_weight":"400","paragraph_spacing":{"unit":"px","size":0,"sizes":[]},"__globals__":{"typography_typography":""},"pa_condition_repeater":[],"typography_typography":"custom","_element_id":"ob-stepbystep-step2-description"},"elements":[],"isInner":false,"widgetType":"text-editor","elType":"widget"}],"isInner":true,"elType":"container"},{"id":"70c963f6","settings":{"text":"Learn more","button_text_color":"#0085FF","background_color":"#0085FF00","border_border":"none","text_padding":{"unit":"px","top":"0","right":"0","bottom":"0","left":"0","isLinked":true},"__globals__":{"button_text_color":"globals\/colors?id=astglobalcolor0","background_color":"","hover_color":"globals\/colors?id=astglobalcolor1"},"pa_condition_repeater":[]},"elements":[],"isInner":false,"widgetType":"button","elType":"widget"}],"isInner":true,"elType":"container"},{"id":"6ea89daf","settings":{"content_width":"full","flex_gap":{"column":"16","row":"16","isLinked":true,"unit":"px","size":16},"padding":{"unit":"px","top":"0","right":"0","bottom":"0","left":"0","isLinked":true},"pa_condition_repeater":[]},"elements":[{"id":"2a623dc8","settings":{"title":"03","header_size":"h4","__globals__":{"title_color":"globals\/colors?id=astglobalcolor3"},"pa_condition_repeater":[]},"elements":[],"isInner":false,"widgetType":"heading","elType":"widget"},{"id":"a96d783","settings":{"image":{"id":"","url":"\/wp-content\/plugins\/obsia\/designs\/placeholders\/person1.webp","source":"url","size":"","alt":""},"pa_condition_repeater":[]},"elements":[],"isInner":false,"widgetType":"image","elType":"widget"},{"id":"64560942","settings":{"content_width":"full","flex_gap":{"column":"4","row":"4","isLinked":true,"unit":"px","size":4},"padding":{"unit":"px","top":"0","right":"0","bottom":"0","left":"0","isLinked":true},"pa_condition_repeater":[]},"elements":[{"id":"7a26ad05","settings":{"title":"Ut Enim Ad Minim Veniam","header_size":"h5","pa_condition_repeater":[],"_element_id":"ob-stepbystep-step3-title"},"elements":[],"isInner":false,"widgetType":"heading","elType":"widget"},{"id":"2bdb1dd","settings":{"editor":"<p>Mi tincidunt elit, id quisque ligula ac diam, amet. Vel etiam suspendisse morbi eleifend faucibus eget vestibulum felis. Dictum quis montes, sit sit. Tellus aliquam enim urna, etiam.<\/p>","typography_font_weight":"400","paragraph_spacing":{"unit":"px","size":0,"sizes":[]},"__globals__":{"typography_typography":""},"pa_condition_repeater":[],"typography_typography":"custom","_element_id":"ob-stepbystep-step3-description"},"elements":[],"isInner":false,"widgetType":"text-editor","elType":"widget"}],"isInner":true,"elType":"container"},{"id":"683bcf2f","settings":{"text":"Learn more","button_text_color":"#0085FF","background_color":"#0085FF00","border_border":"none","text_padding":{"unit":"px","top":"0","right":"0","bottom":"0","left":"0","isLinked":true},"__globals__":{"button_text_color":"globals\/colors?id=astglobalcolor0","background_color":"","hover_color":"globals\/colors?id=astglobalcolor1"},"pa_condition_repeater":[]},"elements":[],"isInner":false,"widgetType":"button","elType":"widget"}],"isInner":true,"elType":"container"}],"isInner":true,"elType":"container"}],"isInner":false,"elType":"container"},{"id":"14567761","settings":{"flex_direction":"column","flex_gap":{"column":"64","row":"64","isLinked":true,"unit":"px","size":64},"background_background":"classic","__globals__":{"background_color":"globals\/colors?id=astglobalcolor4"},"flex_gap_mobile":{"column":"48","row":"48","isLinked":true,"unit":"px","size":48},"pa_condition_repeater":[],"padding":{"unit":"px","top":"50","right":"50","bottom":"50","left":"50","isLinked":true}},"elements":[{"id":"12425f08","settings":{"content_width":"full","flex_direction":"column","flex_justify_content":"space-between","flex_align_items":"center","flex_gap":{"column":"12","row":"12","isLinked":true,"unit":"px","size":12},"padding":{"unit":"px","top":"0","right":"0","bottom":"0","left":"0","isLinked":true},"pa_condition_repeater":[]},"elements":[{"id":"2aa46541","settings":{"title":"Lorem Ipsum Dolor Sit Amet","header_size":"h5","__globals__":{"title_color":"globals\/colors?id=astglobalcolor0"},"pa_condition_repeater":[],"_element_id":"ob-testimonial-tagline"},"elements":[],"isInner":false,"widgetType":"heading","elType":"widget"},{"id":"e46a9e6","settings":{"title":"Ut Enim Ad Minim Veniam","pa_condition_repeater":[],"_element_id":"ob-testimonial-title"},"elements":[],"isInner":false,"widgetType":"heading","elType":"widget"}],"isInner":true,"elType":"container"},{"id":"17e3189a","settings":{"content_width":"full","flex_direction":"row","flex_gap":{"column":"32","row":"32","isLinked":true,"unit":"px","size":32},"padding":{"unit":"px","top":"0","right":"0","bottom":"0","left":"0","isLinked":true},"flex_gap_mobile":{"column":"40","row":"40","isLinked":true,"unit":"px","size":40},"pa_condition_repeater":[]},"elements":[{"id":"6e4782bf","settings":{"content_width":"full","flex_gap":{"column":"40","row":"40","isLinked":true,"unit":"px","size":40},"padding":{"unit":"px","top":"0","right":"0","bottom":"0","left":"0","isLinked":true},"flex_gap_mobile":{"column":"26","row":"26","isLinked":true,"unit":"px","size":26},"pa_condition_repeater":[]},"elements":[{"id":"57221bc7","settings":{"editor":"<p>\u201cMi tincidunt elit, id quisque ligula ac diam, amet. Vel etiam suspendisse morbi eleifend faucibus eget vestibulum felis. Dictum quis montes, sit sit. Tellus aliquam enim urna, etiam.\u201d<\/p>","paragraph_spacing":{"unit":"px","size":0,"sizes":[]},"pa_condition_repeater":[],"_element_id":"ob-testimonial-review1-text"},"elements":[],"isInner":false,"widgetType":"text-editor","elType":"widget"},{"id":"7e48dfa5","settings":{"content_width":"full","flex_direction":"row","flex_gap":{"column":"32","row":"32","isLinked":true,"unit":"px","size":32},"padding":{"unit":"px","top":"0","right":"0","bottom":"0","left":"0","isLinked":true},"width_mobile":{"unit":"%","size":"","sizes":[]},"flex_direction_mobile":"row","flex_wrap_mobile":"nowrap","presetTitle":"Container","presetIcon":"eicon-container","pa_condition_repeater":[]},"elements":[{"id":"f067de9","settings":{"width":{"unit":"px","size":56,"sizes":[]},"width_tablet":{"unit":"px","size":"","sizes":[]},"width_mobile":{"unit":"px","size":"","sizes":[]},"_element_custom_width":{"unit":"px","size":"","sizes":[]},"_flex_align_self":"flex-start","image":{"id":"","url":"\/wp-content\/plugins\/obsia\/designs\/placeholders\/person3.webp","source":"url","size":""},"image_size":"thumbnail","image_border_radius":{"unit":"px","top":"999","right":"999","bottom":"999","left":"999","isLinked":true},"pa_condition_repeater":[]},"elements":[],"isInner":false,"widgetType":"image","elType":"widget"},{"id":"1982e071","settings":{"content_width":"full","flex_gap":{"column":"4","row":"4","isLinked":true,"unit":"px","size":4},"padding":{"unit":"px","top":"0","right":"0","bottom":"0","left":"0","isLinked":true},"flex_justify_content":"center","width_mobile":{"unit":"%","size":100,"sizes":[]},"pa_condition_repeater":[]},"elements":[{"id":"633e38df","settings":{"title":"Ut Enim Ad Minim Veniam","header_size":"h5","pa_condition_repeater":[],"_element_id":"ob-testimonial-review1-author-name"},"elements":[],"isInner":false,"widgetType":"heading","elType":"widget"},{"id":"5830db8e","settings":{"title":"Excepteur Sint Occaecat","header_size":"h6","typography_typography":"custom","typography_font_weight":"400","pa_condition_repeater":[],"_element_id":"ob-testimonial-review1-author-role"},"elements":[],"isInner":false,"widgetType":"heading","elType":"widget"}],"isInner":true,"elType":"container"}],"isInner":true,"elType":"container"}],"isInner":true,"elType":"container"},{"id":"168f5665","settings":{"content_width":"full","flex_gap":{"column":"40","row":"40","isLinked":true,"unit":"px","size":40},"padding":{"unit":"px","top":"0","right":"0","bottom":"0","left":"0","isLinked":true},"flex_gap_mobile":{"column":"26","row":"26","isLinked":true,"unit":"px","size":26},"pa_condition_repeater":[]},"elements":[{"id":"1406ecd0","settings":{"editor":"<p>\u201cMi tincidunt elit, id quisque ligula ac diam, amet. Vel etiam suspendisse morbi eleifend faucibus eget vestibulum felis. Dictum quis montes, sit sit. Tellus aliquam enim urna, etiam.\u201d<\/p>","paragraph_spacing":{"unit":"px","size":0,"sizes":[]},"pa_condition_repeater":[],"_element_id":"ob-testimonial-review2-text"},"elements":[],"isInner":false,"widgetType":"text-editor","elType":"widget"},{"id":"55ac59fe","settings":{"content_width":"full","flex_direction":"row","flex_gap":{"column":"32","row":"32","isLinked":true,"unit":"px","size":32},"padding":{"unit":"px","top":"0","right":"0","bottom":"0","left":"0","isLinked":true},"width_mobile":{"unit":"%","size":"","sizes":[]},"flex_direction_mobile":"row","flex_wrap_mobile":"nowrap","presetTitle":"Container","presetIcon":"eicon-container","pa_condition_repeater":[]},"elements":[{"id":"4b4183ed","settings":{"width":{"unit":"px","size":56,"sizes":[]},"width_tablet":{"unit":"px","size":"","sizes":[]},"width_mobile":{"unit":"px","size":"","sizes":[]},"_element_custom_width":{"unit":"px","size":"","sizes":[]},"_flex_align_self":"flex-start","image":{"id":"","url":"\/wp-content\/plugins\/obsia\/designs\/placeholders\/person3.webp","source":"url","size":""},"image_size":"thumbnail","image_border_radius":{"unit":"px","top":"999","right":"999","bottom":"999","left":"999","isLinked":true},"pa_condition_repeater":[]},"elements":[],"isInner":false,"widgetType":"image","elType":"widget"},{"id":"647ef294","settings":{"content_width":"full","flex_gap":{"column":"4","row":"4","isLinked":true,"unit":"px","size":4},"padding":{"unit":"px","top":"0","right":"0","bottom":"0","left":"0","isLinked":true},"flex_justify_content":"center","width_mobile":{"unit":"%","size":100,"sizes":[]},"pa_condition_repeater":[]},"elements":[{"id":"75463e0","settings":{"title":"Ut Enim Ad Minim Veniam","header_size":"h5","pa_condition_repeater":[],"_element_id":"ob-testimonial-review2-author-name"},"elements":[],"isInner":false,"widgetType":"heading","elType":"widget"},{"id":"10b4e573","settings":{"title":"Excepteur Sint Occaecat","header_size":"h6","typography_typography":"custom","typography_font_weight":"400","pa_condition_repeater":[],"_element_id":"ob-testimonial-review2-author-role"},"elements":[],"isInner":false,"widgetType":"heading","elType":"widget"}],"isInner":true,"elType":"container"}],"isInner":true,"elType":"container"}],"isInner":true,"elType":"container"}],"isInner":true,"elType":"container"}],"isInner":false,"elType":"container"},{"id":"2ed563da","settings":{"flex_direction":"column","min_height":{"unit":"px","size":566,"sizes":[]},"flex_justify_content":"center","flex_gap":{"column":"32","row":"32","isLinked":true,"unit":"px","size":32},"background_background":"classic","background_image":{"id":"","url":"","source":"url","size":""},"background_position":"center center","background_size":"cover","background_overlay_background":"classic","background_overlay_color":"#000000","background_overlay_opacity":{"unit":"px","size":0.59999999999999998,"sizes":[]},"min_height_tablet":{"unit":"px","size":466,"sizes":[]},"pa_condition_repeater":[],"padding":{"unit":"px","top":"50","right":"50","bottom":"50","left":"50","isLinked":true}},"elements":[{"id":"370163e6","settings":{"image":{"url":"\/wp-content\/plugins\/obsia\/designs\/aspera\/images\/city.webp","id":"","size":"","source":"url"},"width":{"unit":"%","size":100,"sizes":[]},"_element_width":"inherit","_position":"absolute","_offset_orientation_v":"end","_z_index":-1,"_element_id":"ob-cta-bg"},"elements":[],"isInner":false,"widgetType":"image","elType":"widget"},{"id":"67ff3de5","settings":{"content_width":"full","flex_align_items":"center","flex_gap":{"column":"12","row":"12","isLinked":true,"unit":"px","size":12},"padding":{"unit":"px","top":"0","right":"0","bottom":"0","left":"0","isLinked":true},"pa_condition_repeater":[]},"elements":[{"id":"765282e7","settings":{"title":"Lorem Ipsum Dolor Sit Amet","header_size":"h5","title_color":"#FFFFFF","pa_condition_repeater":[],"_element_id":"ob-cta-tagline"},"elements":[],"isInner":false,"widgetType":"heading","elType":"widget"},{"id":"38b194ec","settings":{"title":"Ut Enim Ad Minim Veniam","title_color":"#FFFFFF","pa_condition_repeater":[],"_element_id":"ob-cta-title"},"elements":[],"isInner":false,"widgetType":"heading","elType":"widget"}],"isInner":true,"elType":"container"},{"id":"30c52d50","settings":{"text":"Click here","align":"center","button_text_color":"#FFFFFF","align_mobile":"justify","pa_condition_repeater":[],"border_border":"solid","border_color":"#FFFFFF","__globals__":{"button_hover_border_color":"globals\/colors?id=astglobalcolor1"},"_element_id":"ob-cta-button"},"elements":[],"isInner":false,"widgetType":"button","elType":"widget"}],"isInner":false,"elType":"container"}],"page_settings":{"hide_title":"yes"},"version":"0.4","title":"Home","type":"page"}